main/test/20-video/video.v
// verilator lint_off WIDTH
module video
(
    input               CLK,
    input               RESET_N,

    // Вывод на
    output reg  [3:0]   R,
    output reg  [3:0]   G,
    output reg  [3:0]   B,
    output              HS,
    output              VS,

    // Устройство занято
    output reg          BUSY,

    // Физический интерфейс DRAM
    output              DRAM_CLK,       // Тактовая частота памяти 25 MHZ
    output reg  [ 1:0]  DRAM_BA,        // 4 банка
    output reg  [12:0]  DRAM_ADDR,      // Максимальный адрес 2^13=8192
    inout       [15:0]  DRAM_DQ,        // Ввод-вывод
    output reg          DRAM_CAS,       // CAS
    output reg          DRAM_RAS,       // RAS
    output reg          DRAM_WE,        // WE
    output reg          DRAM_LDQM,      // Маска для младшего байта
    output reg          DRAM_UDQM       // Маска для старшего байта
);

// Направление данных (in, out), если dram_we=0, то запись; иначе чтение
assign DRAM_DQ      = DRAM_WE ? 16'hZZZZ : {data_i, data_i};
assign DRAM_CLK     = CLK;

// Команды
localparam
    //                   RCW
    cmd_loadmode    = 3'b000,
    cmd_refresh     = 3'b001,
    cmd_precharge   = 3'b010,
    cmd_activate    = 3'b011,
    cmd_write       = 3'b100,
    cmd_read        = 3'b101,
    cmd_burst_term  = 3'b110,
    cmd_nop         = 3'b111;

`ifdef ICARUS
localparam INIT_TIME = 0;
`else
localparam INIT_TIME = 1250;    // 25 ns x 1250 (31 mks)
`endif

`define RCW {DRAM_RAS,DRAM_CAS,DRAM_WE}

// DRAM
// ---------------------------------------------------------------------
reg [10:0]  ic;         // 0..2047
reg [ 7:0]  data_i;
reg         reset;
// ---------------------------------------------------------------------
// Тайминги для горизонтальной|вертикальной развертки (640x480)
parameter
    hz_back    = 48,  vt_back    = 33,  // 35  | 33
    hz_visible = 640, vt_visible = 480, // 400 | 480
    hz_front   = 16,  vt_front   = 10,  // 12  | 10
    hz_sync    = 96,  vt_sync    = 2,   // 2   | 2
    hz_whole   = 800, vt_whole   = 525; // 449 | 525
// ---------------------------------------------------------------------
assign HS = x  < (hz_back + hz_visible + hz_front); // NEG.
assign VS = y >= (vt_back + vt_visible + vt_front); // POS.
// ---------------------------------------------------------------------
wire        xmax = (x == hz_whole - 1);
wire        ymax = (y == vt_whole - 1);
reg  [ 9:0] x    = 0;
reg  [ 9:0] y    = 0;
wire [ 9:0] X    = x - hz_back;
wire [ 9:0] Y    = y - vt_back;
// ---------------------------------------------------------------------
wire        paperx = x >= hz_back && x < hz_back + hz_visible;
wire        papery = y >= vt_back && y < vt_back + vt_visible;
wire        paper  = paperx && papery;
// ---------------------------------------------------------------------

// Вывод видеосигнала
always @(negedge CLK)
if (RESET_N == 0) begin

    reset       <= 1;
    ic          <= 0;
    BUSY        <= 0;
    DRAM_ADDR   <= 0;
    DRAM_LDQM   <= 1;
    DRAM_UDQM   <= 1;
    DRAM_BA     <= 0;

end
else if (reset) begin

    ic <= ic + 1;

    case (ic)

        INIT_TIME + 0:  begin `RCW  <= cmd_precharge; end
        INIT_TIME + 3:  begin `RCW  <= cmd_refresh;   end
        INIT_TIME + 17: begin `RCW  <= cmd_loadmode; DRAM_ADDR[9:0] <= 10'b0_00_010_0_111; end
        INIT_TIME + 20: begin ic <= 0; reset <= 0; end
        default:        begin `RCW  <= cmd_nop; end

    endcase

end
else begin

    BUSY <= 0;
    {R,G,B} <= 12'h000;

    // Кадровая развертка
    x <= xmax ?         0 : x + 1;
    y <= xmax ? (ymax ? 0 : y + 1) : y;

    // Вывод окна видеоадаптера
    if (paper) {R,G,B} <= 12'hFFF;

    // Обновление видимых строк
    if (x <= 256+3 && papery) begin

        BUSY <= 1;

        case (x)
        // Запрос строки
        0: begin

            `RCW        <= cmd_activate;
            DRAM_BA     <= 2'b00;
            DRAM_ADDR   <= Y[8:2];            // Y=0..383
            DRAM_UDQM   <= 1'b0;
            DRAM_LDQM   <= 1'b0;

        end
        // Ожидание открытия строки
        1,3: begin `RCW <= cmd_nop; end
        // Выбор стартовой колонки (256 байт x 4 строки)
        2: begin

            `RCW        <= cmd_read;
            DRAM_ADDR   <= {Y[1:0], 8'h00};

        end
        // Запрос PRECHARGE
        256+3: begin

            `RCW <= cmd_precharge;
            DRAM_ADDR[10] <= 1'b1;

        end
        // Считывание 256 WORD
        default: begin

            // sram_o  <= DRAM_DQ;
            // sram_we <= 1;
            DRAM_ADDR[7:0] <= DRAM_ADDR[7:0] + 1;

        end
        endcase

    end
end

endmodule

main/test/20-video/tb.v
`timescale 10ns / 1ns
module tb;
// ---------------------------------------------------------------------
reg         clock, clock25, reset_n;
always #0.5 clock       = ~clock;
always #2.0 clock25     = ~clock25;
// ---------------------------------------------------------------------
initial begin reset_n = 0; clock = 0; clock25 = 0; #3.0 reset_n = 1; #2500 $finish; end
initial begin $dumpfile("tb.vcd"); $dumpvars(0, tb); end
// ---------------------------------------------------------------------
wire [3:0]  vga_r, vga_g, vga_b;
wire        vga_hs, vga_vs;
wire        dram_clk, dram_cas, dram_ras, dram_udqm, dram_ldqm;
wire [15:0] dram_dq;
wire [12:0] dram_addr;
wire [ 1:0] dram_ba;
// ---------------------------------------------------------------------
video VIDEO
(
    .CLK        (clock25),
    .RESET_N    (reset_n),
    .R          (vga_r),
    .G          (vga_g),
    .B          (vga_b),
    .HS         (vga_hs),
    .VS         (vga_vs),
    .DRAM_CLK   (dram_clk),
    .DRAM_BA    (dram_ba),
    .DRAM_ADDR  (dram_addr),
    .DRAM_DQ    (dram_dq),
    .DRAM_CAS   (dram_cas),
    .DRAM_RAS   (dram_ras),
    .DRAM_WE    (dram_w),
    .DRAM_LDQM  (dram_ldqm),
    .DRAM_UDQM  (dram_udqm)
);

endmodule

main/test/20-video/tb.vcd
$date
	Sat Mar  8 21:38:32 2025
$end
$version
	Icarus Verilog
$end
$timescale
	1ns
$end
$scope module tb $end
$var wire 1 ! vga_vs $end
$var wire 4 " vga_r [3:0] $end
$var wire 1 # vga_hs $end
$var wire 4 $ vga_g [3:0] $end
$var wire 4 % vga_b [3:0] $end
$var wire 1 & dram_w $end
$var wire 1 ' dram_udqm $end
$var wire 1 ( dram_ras $end
$var wire 1 ) dram_ldqm $end
$var wire 16 * dram_dq [15:0] $end
$var wire 1 + dram_clk $end
$var wire 1 , dram_cas $end
$var wire 2 - dram_ba [1:0] $end
$var wire 13 . dram_addr [12:0] $end
$var reg 1 / clock $end
$var reg 1 0 clock25 $end
$var reg 1 1 reset_n $end
$scope module VIDEO $end
$var wire 1 0 CLK $end
$var wire 1 + DRAM_CLK $end
$var wire 1 1 RESET_N $end
$var wire 1 2 paper $end
$var wire 1 3 paperx $end
$var wire 1 4 papery $end
$var wire 1 5 ymax $end
$var wire 1 6 xmax $end
$var wire 10 7 Y [9:0] $end
$var wire 10 8 X [9:0] $end
$var wire 1 ! VS $end
$var wire 1 # HS $end
$var wire 16 9 DRAM_DQ [15:0] $end
$var parameter 32 : INIT_TIME $end
$var parameter 3 ; cmd_activate $end
$var parameter 3 < cmd_burst_term $end
$var parameter 3 = cmd_loadmode $end
$var parameter 3 > cmd_nop $end
$var parameter 3 ? cmd_precharge $end
$var parameter 3 @ cmd_read $end
$var parameter 3 A cmd_refresh $end
$var parameter 3 B cmd_write $end
$var parameter 32 C hz_back $end
$var parameter 32 D hz_front $end
$var parameter 32 E hz_sync $end
$var parameter 32 F hz_visible $end
$var parameter 32 G hz_whole $end
$var parameter 32 H vt_back $end
$var parameter 32 I vt_front $end
$var parameter 32 J vt_sync $end
$var parameter 32 K vt_visible $end
$var parameter 32 L vt_whole $end
$var reg 4 M B [3:0] $end
$var reg 1 N BUSY $end
$var reg 13 O DRAM_ADDR [12:0] $end
$var reg 2 P DRAM_BA [1:0] $end
$var reg 1 , DRAM_CAS $end
$var reg 1 ) DRAM_LDQM $end
$var reg 1 ( DRAM_RAS $end
$var reg 1 ' DRAM_UDQM $end
$var reg 1 & DRAM_WE $end
$var reg 4 Q G [3:0] $end
$var reg 4 R R [3:0] $end
$var reg 8 S data_i [7:0] $end
$var reg 11 T ic [10:0] $end
$var reg 1 U reset $end
$var reg 10 V x [9:0] $end
$var reg 10 W y [9:0] $end
$upscope $end
$upscope $end
$enddefinitions $end
$comment Show the parameter values. $end
$dumpall
b1000001101 L
b111100000 K
b10 J
b1010 I
b100001 H
b1100100000 G
b1010000000 F
b1100000 E
b10000 D
b110000 C
b100 B
b1 A
b101 @
b10 ?
b111 >
b0 =
b110 <
b11 ;
b0 :
$end
#0
$dumpvars
b0 W
b0 V
1U
b0 T
bx S
bx R
bx Q
b0 P
b0 O
0N
bx M
bx 9
b1111010000 8
b1111011111 7
06
05
04
03
02
01
00
0/
b0 .
b0 -
x,
0+
bx *
1)
x(
1'
x&
bx %
bx $
1#
bx "
0!
$end
#5
1/
#10
0/
#15
1/
#20
0/
1+
10
#25
1/
#30
0/
11
#35
1/
#40
0(
1,
0&
b1 T
0/
0+
00
#45
1/
#50
0/
#55
1/
#60
0/
1+
10
#65
1/
#70
0/
#75
1/
#80
bz *
bz 9
1(
1&
b10 T
0/
0+
00
#85
1/
#90
0/
#95
1/
#100
0/
1+
10
#105
1/
#110
0/
#115
1/
#120
b11 T
0/
0+
00
#125
1/
#130
0/
#135
1/
#140
0/
1+
10
#145
1/
#150
0/
#155
1/
#160
0(
0,
b100 T
0/
0+
00
#165
1/
#170
0/
#175
1/
#180
0/
1+
10
#185
1/
#190
0/
#195
1/
#200
1(
1,
b101 T
0/
0+
00
#205
1/
#210
0/
#215
1/
#220
0/
1+
10
#225
1/
#230
0/
#235
1/
#240
b110 T
0/
0+
00
#245
1/
#250
0/
#255
1/
#260
0/
1+
10
#265
1/
#270
0/
#275
1/
#280
b111 T
0/
0+
00
#285
1/
#290
0/
#295
1/
#300
0/
1+
10
#305
1/
#310
0/
#315
1/
#320
b1000 T
0/
0+
00
#325
1/
#330
0/
#335
1/
#340
0/
1+
10
#345
1/
#350
0/
#355
1/
#360
b1001 T
0/
0+
00
#365
1/
#370
0/
#375
1/
#380
0/
1+
10
#385
1/
#390
0/
#395
1/
#400
b1010 T
0/
0+
00
#405
1/
#410
0/
#415
1/
#420
0/
1+
10
#425
1/
#430
0/
#435
1/
#440
b1011 T
0/
0+
00
#445
1/
#450
0/
#455
1/
#460
0/
1+
10
#465
1/
#470
0/
#475
1/
#480
b1100 T
0/
0+
00
#485
1/
#490
0/
#495
1/
#500
0/
1+
10
#505
1/
#510
0/
#515
1/
#520
b1101 T
0/
0+
00
#525
1/
#530
0/
#535
1/
#540
0/
1+
10
#545
1/
#550
0/
#555
1/
#560
b1110 T
0/
0+
00
#565
1/
#570
0/
#575
1/
#580
0/
1+
10
#585
1/
#590
0/
#595
1/
#600
b1111 T
0/
0+
00
#605
1/
#610
0/
#615
1/
#620
0/
1+
10
#625
1/
#630
0/
#635
1/
#640
b10000 T
0/
0+
00
#645
1/
#650
0/
#655
1/
#660
0/
1+
10
#665
1/
#670
0/
#675
1/
#680
b10001 T
0/
0+
00
#685
1/
#690
0/
#695
1/
#700
0/
1+
10
#705
1/
#710
0/
#715
1/
#720
bx *
bx 9
b100111 .
b100111 O
0(
0,
0&
b10010 T
0/
0+
00
#725
1/
#730
0/
#735
1/
#740
0/
1+
10
#745
1/
#750
0/
#755
1/
#760
bz *
bz 9
1(
1,
1&
b10011 T
0/
0+
00
#765
1/
#770
0/
#775
1/
#780
0/
1+
10
#785
1/
#790
0/
#795
1/
#800
b10100 T
0/
0+
00
#805
1/
#810
0/
#815
1/
#820
0/
1+
10
#825
1/
#830
0/
#835
1/
#840
0U
b0 T
0/
0+
00
#845
1/
#850
0/
#855
1/
#860
0/
1+
10
#865
1/
#870
0/
#875
1/
#880
b1111010001 8
b1 V
b0 "
b0 R
b0 $
b0 Q
b0 %
b0 M
0/
0+
00
#885
1/
#890
0/
#895
1/
#900
0/
1+
10
#905
1/
#910
0/
#915
1/
#920
b1111010010 8
b10 V
0/
0+
00
#925
1/
#930
0/
#935
1/
#940
0/
1+
10
#945
1/
#950
0/
#955
1/
#960
b1111010011 8
b11 V
0/
0+
00
#965
1/
#970
0/
#975
1/
#980
0/
1+
10
#985
1/
#990
0/
#995
1/
#1000
b1111010100 8
b100 V
0/
0+
00
#1005
1/
#1010
0/
#1015
1/
#1020
0/
1+
10
#1025
1/
#1030
0/
#1035
1/
#1040
b1111010101 8
b101 V
0/
0+
00
#1045
1/
#1050
0/
#1055
1/
#1060
0/
1+
10
#1065
1/
#1070
0/
#1075
1/
#1080
b1111010110 8
b110 V
0/
0+
00
#1085
1/
#1090
0/
#1095
1/
#1100
0/
1+
10
#1105
1/
#1110
0/
#1115
1/
#1120
b1111010111 8
b111 V
0/
0+
00
#1125
1/
#1130
0/
#1135
1/
#1140
0/
1+
10
#1145
1/
#1150
0/
#1155
1/
#1160
b1111011000 8
b1000 V
0/
0+
00
#1165
1/
#1170
0/
#1175
1/
#1180
0/
1+
10
#1185
1/
#1190
0/
#1195
1/
#1200
b1111011001 8
b1001 V
0/
0+
00
#1205
1/
#1210
0/
#1215
1/
#1220
0/
1+
10
#1225
1/
#1230
0/
#1235
1/
#1240
b1111011010 8
b1010 V
0/
0+
00
#1245
1/
#1250
0/
#1255
1/
#1260
0/
1+
10
#1265
1/
#1270
0/
#1275
1/
#1280
b1111011011 8
b1011 V
0/
0+
00
#1285
1/
#1290
0/
#1295
1/
#1300
0/
1+
10
#1305
1/
#1310
0/
#1315
1/
#1320
b1111011100 8
b1100 V
0/
0+
00
#1325
1/
#1330
0/
#1335
1/
#1340
0/
1+
10
#1345
1/
#1350
0/
#1355
1/
#1360
b1111011101 8
b1101 V
0/
0+
00
#1365
1/
#1370
0/
#1375
1/
#1380
0/
1+
10
#1385
1/
#1390
0/
#1395
1/
#1400
b1111011110 8
b1110 V
0/
0+
00
#1405
1/
#1410
0/
#1415
1/
#1420
0/
1+
10
#1425
1/
#1430
0/
#1435
1/
#1440
b1111011111 8
b1111 V
0/
0+
00
#1445
1/
#1450
0/
#1455
1/
#1460
0/
1+
10
#1465
1/
#1470
0/
#1475
1/
#1480
b1111100000 8
b10000 V
0/
0+
00
#1485
1/
#1490
0/
#1495
1/
#1500
0/
1+
10
#1505
1/
#1510
0/
#1515
1/
#1520
b1111100001 8
b10001 V
0/
0+
00
#1525
1/
#1530
0/
#1535
1/
#1540
0/
1+
10
#1545
1/
#1550
0/
#1555
1/
#1560
b1111100010 8
b10010 V
0/
0+
00
#1565
1/
#1570
0/
#1575
1/
#1580
0/
1+
10
#1585
1/
#1590
0/
#1595
1/
#1600
b1111100011 8
b10011 V
0/
0+
00
#1605
1/
#1610
0/
#1615
1/
#1620
0/
1+
10
#1625
1/
#1630
0/
#1635
1/
#1640
b1111100100 8
b10100 V
0/
0+
00
#1645
1/
#1650
0/
#1655
1/
#1660
0/
1+
10
#1665
1/
#1670
0/
#1675
1/
#1680
b1111100101 8
b10101 V
0/
0+
00
#1685
1/
#1690
0/
#1695
1/
#1700
0/
1+
10
#1705
1/
#1710
0/
#1715
1/
#1720
b1111100110 8
b10110 V
0/
0+
00
#1725
1/
#1730
0/
#1735
1/
#1740
0/
1+
10
#1745
1/
#1750
0/
#1755
1/
#1760
b1111100111 8
b10111 V
0/
0+
00
#1765
1/
#1770
0/
#1775
1/
#1780
0/
1+
10
#1785
1/
#1790
0/
#1795
1/
#1800
b1111101000 8
b11000 V
0/
0+
00
#1805
1/
#1810
0/
#1815
1/
#1820
0/
1+
10
#1825
1/
#1830
0/
#1835
1/
#1840
b1111101001 8
b11001 V
0/
0+
00
#1845
1/
#1850
0/
#1855
1/
#1860
0/
1+
10
#1865
1/
#1870
0/
#1875
1/
#1880
b1111101010 8
b11010 V
0/
0+
00
#1885
1/
#1890
0/
#1895
1/
#1900
0/
1+
10
#1905
1/
#1910
0/
#1915
1/
#1920
b1111101011 8
b11011 V
0/
0+
00
#1925
1/
#1930
0/
#1935
1/
#1940
0/
1+
10
#1945
1/
#1950
0/
#1955
1/
#1960
b1111101100 8
b11100 V
0/
0+
00
#1965
1/
#1970
0/
#1975
1/
#1980
0/
1+
10
#1985
1/
#1990
0/
#1995
1/
#2000
b1111101101 8
b11101 V
0/
0+
00
#2005
1/
#2010
0/
#2015
1/
#2020
0/
1+
10
#2025
1/
#2030
0/
#2035
1/
#2040
b1111101110 8
b11110 V
0/
0+
00
#2045
1/
#2050
0/
#2055
1/
#2060
0/
1+
10
#2065
1/
#2070
0/
#2075
1/
#2080
b1111101111 8
b11111 V
0/
0+
00
#2085
1/
#2090
0/
#2095
1/
#2100
0/
1+
10
#2105
1/
#2110
0/
#2115
1/
#2120
b1111110000 8
b100000 V
0/
0+
00
#2125
1/
#2130
0/
#2135
1/
#2140
0/
1+
10
#2145
1/
#2150
0/
#2155
1/
#2160
b1111110001 8
b100001 V
0/
0+
00
#2165
1/
#2170
0/
#2175
1/
#2180
0/
1+
10
#2185
1/
#2190
0/
#2195
1/
#2200
b1111110010 8
b100010 V
0/
0+
00
#2205
1/
#2210
0/
#2215
1/
#2220
0/
1+
10
#2225
1/
#2230
0/
#2235
1/
#2240
b1111110011 8
b100011 V
0/
0+
00
#2245
1/
#2250
0/
#2255
1/
#2260
0/
1+
10
#2265
1/
#2270
0/
#2275
1/
#2280
b1111110100 8
b100100 V
0/
0+
00
#2285
1/
#2290
0/
#2295
1/
#2300
0/
1+
10
#2305
1/
#2310
0/
#2315
1/
#2320
b1111110101 8
b100101 V
0/
0+
00
#2325
1/
#2330
0/
#2335
1/
#2340
0/
1+
10
#2345
1/
#2350
0/
#2355
1/
#2360
b1111110110 8
b100110 V
0/
0+
00
#2365
1/
#2370
0/
#2375
1/
#2380
0/
1+
10
#2385
1/
#2390
0/
#2395
1/
#2400
b1111110111 8
b100111 V
0/
0+
00
#2405
1/
#2410
0/
#2415
1/
#2420
0/
1+
10
#2425
1/
#2430
0/
#2435
1/
#2440
b1111111000 8
b101000 V
0/
0+
00
#2445
1/
#2450
0/
#2455
1/
#2460
0/
1+
10
#2465
1/
#2470
0/
#2475
1/
#2480
b1111111001 8
b101001 V
0/
0+
00
#2485
1/
#2490
0/
#2495
1/
#2500
0/
1+
10
#2505
1/
#2510
0/
#2515
1/
#2520
b1111111010 8
b101010 V
0/
0+
00
#2525
1/
#2530
0/
#2535
1/
#2540
0/
1+
10
#2545
1/
#2550
0/
#2555
1/
#2560
b1111111011 8
b101011 V
0/
0+
00
#2565
1/
#2570
0/
#2575
1/
#2580
0/
1+
10
#2585
1/
#2590
0/
#2595
1/
#2600
b1111111100 8
b101100 V
0/
0+
00
#2605
1/
#2610
0/
#2615
1/
#2620
0/
1+
10
#2625
1/
#2630
0/
#2635
1/
#2640
b1111111101 8
b101101 V
0/
0+
00
#2645
1/
#2650
0/
#2655
1/
#2660
0/
1+
10
#2665
1/
#2670
0/
#2675
1/
#2680
b1111111110 8
b101110 V
0/
0+
00
#2685
1/
#2690
0/
#2695
1/
#2700
0/
1+
10
#2705
1/
#2710
0/
#2715
1/
#2720
b1111111111 8
b101111 V
0/
0+
00
#2725
1/
#2730
0/
#2735
1/
#2740
0/
1+
10
#2745
1/
#2750
0/
#2755
1/
#2760
b0 8
13
b110000 V
0/
0+
00
#2765
1/
#2770
0/
#2775
1/
#2780
0/
1+
10
#2785
1/
#2790
0/
#2795
1/
#2800
b1 8
b110001 V
0/
0+
00
#2805
1/
#2810
0/
#2815
1/
#2820
0/
1+
10
#2825
1/
#2830
0/
#2835
1/
#2840
b10 8
b110010 V
0/
0+
00
#2845
1/
#2850
0/
#2855
1/
#2860
0/
1+
10
#2865
1/
#2870
0/
#2875
1/
#2880
b11 8
b110011 V
0/
0+
00
#2885
1/
#2890
0/
#2895
1/
#2900
0/
1+
10
#2905
1/
#2910
0/
#2915
1/
#2920
b100 8
b110100 V
0/
0+
00
#2925
1/
#2930
0/
#2935
1/
#2940
0/
1+
10
#2945
1/
#2950
0/
#2955
1/
#2960
b101 8
b110101 V
0/
0+
00
#2965
1/
#2970
0/
#2975
1/
#2980
0/
1+
10
#2985
1/
#2990
0/
#2995
1/
#3000
b110 8
b110110 V
0/
0+
00
#3005
1/
#3010
0/
#3015
1/
#3020
0/
1+
10
#3025
1/
#3030
0/
#3035
1/
#3040
b111 8
b110111 V
0/
0+
00
#3045
1/
#3050
0/
#3055
1/
#3060
0/
1+
10
#3065
1/
#3070
0/
#3075
1/
#3080
b1000 8
b111000 V
0/
0+
00
#3085
1/
#3090
0/
#3095
1/
#3100
0/
1+
10
#3105
1/
#3110
0/
#3115
1/
#3120
b1001 8
b111001 V
0/
0+
00
#3125
1/
#3130
0/
#3135
1/
#3140
0/
1+
10
#3145
1/
#3150
0/
#3155
1/
#3160
b1010 8
b111010 V
0/
0+
00
#3165
1/
#3170
0/
#3175
1/
#3180
0/
1+
10
#3185
1/
#3190
0/
#3195
1/
#3200
b1011 8
b111011 V
0/
0+
00
#3205
1/
#3210
0/
#3215
1/
#3220
0/
1+
10
#3225
1/
#3230
0/
#3235
1/
#3240
b1100 8
b111100 V
0/
0+
00
#3245
1/
#3250
0/
#3255
1/
#3260
0/
1+
10
#3265
1/
#3270
0/
#3275
1/
#3280
b1101 8
b111101 V
0/
0+
00
#3285
1/
#3290
0/
#3295
1/
#3300
0/
1+
10
#3305
1/
#3310
0/
#3315
1/
#3320
b1110 8
b111110 V
0/
0+
00
#3325
1/
#3330
0/
#3335
1/
#3340
0/
1+
10
#3345
1/
#3350
0/
#3355
1/
#3360
b1111 8
b111111 V
0/
0+
00
#3365
1/
#3370
0/
#3375
1/
#3380
0/
1+
10
#3385
1/
#3390
0/
#3395
1/
#3400
b10000 8
b1000000 V
0/
0+
00
#3405
1/
#3410
0/
#3415
1/
#3420
0/
1+
10
#3425
1/
#3430
0/
#3435
1/
#3440
b10001 8
b1000001 V
0/
0+
00
#3445
1/
#3450
0/
#3455
1/
#3460
0/
1+
10
#3465
1/
#3470
0/
#3475
1/
#3480
b10010 8
b1000010 V
0/
0+
00
#3485
1/
#3490
0/
#3495
1/
#3500
0/
1+
10
#3505
1/
#3510
0/
#3515
1/
#3520
b10011 8
b1000011 V
0/
0+
00
#3525
1/
#3530
0/
#3535
1/
#3540
0/
1+
10
#3545
1/
#3550
0/
#3555
1/
#3560
b10100 8
b1000100 V
0/
0+
00
#3565
1/
#3570
0/
#3575
1/
#3580
0/
1+
10
#3585
1/
#3590
0/
#3595
1/
#3600
b10101 8
b1000101 V
0/
0+
00
#3605
1/
#3610
0/
#3615
1/
#3620
0/
1+
10
#3625
1/
#3630
0/
#3635
1/
#3640
b10110 8
b1000110 V
0/
0+
00
#3645
1/
#3650
0/
#3655
1/
#3660
0/
1+
10
#3665
1/
#3670
0/
#3675
1/
#3680
b10111 8
b1000111 V
0/
0+
00
#3685
1/
#3690
0/
#3695
1/
#3700
0/
1+
10
#3705
1/
#3710
0/
#3715
1/
#3720
b11000 8
b1001000 V
0/
0+
00
#3725
1/
#3730
0/
#3735
1/
#3740
0/
1+
10
#3745
1/
#3750
0/
#3755
1/
#3760
b11001 8
b1001001 V
0/
0+
00
#3765
1/
#3770
0/
#3775
1/
#3780
0/
1+
10
#3785
1/
#3790
0/
#3795
1/
#3800
b11010 8
b1001010 V
0/
0+
00
#3805
1/
#3810
0/
#3815
1/
#3820
0/
1+
10
#3825
1/
#3830
0/
#3835
1/
#3840
b11011 8
b1001011 V
0/
0+
00
#3845
1/
#3850
0/
#3855
1/
#3860
0/
1+
10
#3865
1/
#3870
0/
#3875
1/
#3880
b11100 8
b1001100 V
0/
0+
00
#3885
1/
#3890
0/
#3895
1/
#3900
0/
1+
10
#3905
1/
#3910
0/
#3915
1/
#3920
b11101 8
b1001101 V
0/
0+
00
#3925
1/
#3930
0/
#3935
1/
#3940
0/
1+
10
#3945
1/
#3950
0/
#3955
1/
#3960
b11110 8
b1001110 V
0/
0+
00
#3965
1/
#3970
0/
#3975
1/
#3980
0/
1+
10
#3985
1/
#3990
0/
#3995
1/
#4000
b11111 8
b1001111 V
0/
0+
00
#4005
1/
#4010
0/
#4015
1/
#4020
0/
1+
10
#4025
1/
#4030
0/
#4035
1/
#4040
b100000 8
b1010000 V
0/
0+
00
#4045
1/
#4050
0/
#4055
1/
#4060
0/
1+
10
#4065
1/
#4070
0/
#4075
1/
#4080
b100001 8
b1010001 V
0/
0+
00
#4085
1/
#4090
0/
#4095
1/
#4100
0/
1+
10
#4105
1/
#4110
0/
#4115
1/
#4120
b100010 8
b1010010 V
0/
0+
00
#4125
1/
#4130
0/
#4135
1/
#4140
0/
1+
10
#4145
1/
#4150
0/
#4155
1/
#4160
b100011 8
b1010011 V
0/
0+
00
#4165
1/
#4170
0/
#4175
1/
#4180
0/
1+
10
#4185
1/
#4190
0/
#4195
1/
#4200
b100100 8
b1010100 V
0/
0+
00
#4205
1/
#4210
0/
#4215
1/
#4220
0/
1+
10
#4225
1/
#4230
0/
#4235
1/
#4240
b100101 8
b1010101 V
0/
0+
00
#4245
1/
#4250
0/
#4255
1/
#4260
0/
1+
10
#4265
1/
#4270
0/
#4275
1/
#4280
b100110 8
b1010110 V
0/
0+
00
#4285
1/
#4290
0/
#4295
1/
#4300
0/
1+
10
#4305
1/
#4310
0/
#4315
1/
#4320
b100111 8
b1010111 V
0/
0+
00
#4325
1/
#4330
0/
#4335
1/
#4340
0/
1+
10
#4345
1/
#4350
0/
#4355
1/
#4360
b101000 8
b1011000 V
0/
0+
00
#4365
1/
#4370
0/
#4375
1/
#4380
0/
1+
10
#4385
1/
#4390
0/
#4395
1/
#4400
b101001 8
b1011001 V
0/
0+
00
#4405
1/
#4410
0/
#4415
1/
#4420
0/
1+
10
#4425
1/
#4430
0/
#4435
1/
#4440
b101010 8
b1011010 V
0/
0+
00
#4445
1/
#4450
0/
#4455
1/
#4460
0/
1+
10
#4465
1/
#4470
0/
#4475
1/
#4480
b101011 8
b1011011 V
0/
0+
00
#4485
1/
#4490
0/
#4495
1/
#4500
0/
1+
10
#4505
1/
#4510
0/
#4515
1/
#4520
b101100 8
b1011100 V
0/
0+
00
#4525
1/
#4530
0/
#4535
1/
#4540
0/
1+
10
#4545
1/
#4550
0/
#4555
1/
#4560
b101101 8
b1011101 V
0/
0+
00
#4565
1/
#4570
0/
#4575
1/
#4580
0/
1+
10
#4585
1/
#4590
0/
#4595
1/
#4600
b101110 8
b1011110 V
0/
0+
00
#4605
1/
#4610
0/
#4615
1/
#4620
0/
1+
10
#4625
1/
#4630
0/
#4635
1/
#4640
b101111 8
b1011111 V
0/
0+
00
#4645
1/
#4650
0/
#4655
1/
#4660
0/
1+
10
#4665
1/
#4670
0/
#4675
1/
#4680
b110000 8
b1100000 V
0/
0+
00
#4685
1/
#4690
0/
#4695
1/
#4700
0/
1+
10
#4705
1/
#4710
0/
#4715
1/
#4720
b110001 8
b1100001 V
0/
0+
00
#4725
1/
#4730
0/
#4735
1/
#4740
0/
1+
10
#4745
1/
#4750
0/
#4755
1/
#4760
b110010 8
b1100010 V
0/
0+
00
#4765
1/
#4770
0/
#4775
1/
#4780
0/
1+
10
#4785
1/
#4790
0/
#4795
1/
#4800
b110011 8
b1100011 V
0/
0+
00
#4805
1/
#4810
0/
#4815
1/
#4820
0/
1+
10
#4825
1/
#4830
0/
#4835
1/
#4840
b110100 8
b1100100 V
0/
0+
00
#4845
1/
#4850
0/
#4855
1/
#4860
0/
1+
10
#4865
1/
#4870
0/
#4875
1/
#4880
b110101 8
b1100101 V
0/
0+
00
#4885
1/
#4890
0/
#4895
1/
#4900
0/
1+
10
#4905
1/
#4910
0/
#4915
1/
#4920
b110110 8
b1100110 V
0/
0+
00
#4925
1/
#4930
0/
#4935
1/
#4940
0/
1+
10
#4945
1/
#4950
0/
#4955
1/
#4960
b110111 8
b1100111 V
0/
0+
00
#4965
1/
#4970
0/
#4975
1/
#4980
0/
1+
10
#4985
1/
#4990
0/
#4995
1/
#5000
b111000 8
b1101000 V
0/
0+
00
#5005
1/
#5010
0/
#5015
1/
#5020
0/
1+
10
#5025
1/
#5030
0/
#5035
1/
#5040
b111001 8
b1101001 V
0/
0+
00
#5045
1/
#5050
0/
#5055
1/
#5060
0/
1+
10
#5065
1/
#5070
0/
#5075
1/
#5080
b111010 8
b1101010 V
0/
0+
00
#5085
1/
#5090
0/
#5095
1/
#5100
0/
1+
10
#5105
1/
#5110
0/
#5115
1/
#5120
b111011 8
b1101011 V
0/
0+
00
#5125
1/
#5130
0/
#5135
1/
#5140
0/
1+
10
#5145
1/
#5150
0/
#5155
1/
#5160
b111100 8
b1101100 V
0/
0+
00
#5165
1/
#5170
0/
#5175
1/
#5180
0/
1+
10
#5185
1/
#5190
0/
#5195
1/
#5200
b111101 8
b1101101 V
0/
0+
00
#5205
1/
#5210
0/
#5215
1/
#5220
0/
1+
10
#5225
1/
#5230
0/
#5235
1/
#5240
b111110 8
b1101110 V
0/
0+
00
#5245
1/
#5250
0/
#5255
1/
#5260
0/
1+
10
#5265
1/
#5270
0/
#5275
1/
#5280
b111111 8
b1101111 V
0/
0+
00
#5285
1/
#5290
0/
#5295
1/
#5300
0/
1+
10
#5305
1/
#5310
0/
#5315
1/
#5320
b1000000 8
b1110000 V
0/
0+
00
#5325
1/
#5330
0/
#5335
1/
#5340
0/
1+
10
#5345
1/
#5350
0/
#5355
1/
#5360
b1000001 8
b1110001 V
0/
0+
00
#5365
1/
#5370
0/
#5375
1/
#5380
0/
1+
10
#5385
1/
#5390
0/
#5395
1/
#5400
b1000010 8
b1110010 V
0/
0+
00
#5405
1/
#5410
0/
#5415
1/
#5420
0/
1+
10
#5425
1/
#5430
0/
#5435
1/
#5440
b1000011 8
b1110011 V
0/
0+
00
#5445
1/
#5450
0/
#5455
1/
#5460
0/
1+
10
#5465
1/
#5470
0/
#5475
1/
